fix8.py
fix8-0.1.9.dist-info/METADATA
fix8-0.1.9.dist-info/WHEEL
fix8-0.1.9.dist-info/entry_points.txt
fix8-0.1.9.dist-info/top_level.txt
fix8-0.1.9.dist-info/zip-safe
fix8-0.1.9.dist-info/RECORD
