Metadata-Version: 2.1
Name: fix8
Version: 0.1.9
Summary: Automatic fix for Python linting issues found by Flake8
Home-page: https://github.com/PeterJCLaw/fix8
Author: Peter Law
Author-email: PeterJCLaw@gmail.com
License: UNKNOWN
Project-URL: Documentation, https://github.com/PeterJCLaw/fix8/blob/master/README.md
Project-URL: Code, https://github.com/PeterJCLaw/fix8
Project-URL: Issue tracker, https://github.com/PeterJCLaw/fix8/issues
Platform: UNKNOWN
Classifier: Intended Audience :: Developers
Classifier: Operating System :: OS Independent
Classifier: Programming Language :: Python :: 3
Classifier: Programming Language :: Python :: 3.7
Classifier: Programming Language :: Python :: 3.8
Classifier: Programming Language :: Python :: 3.9
Classifier: Programming Language :: Python :: 3.10
Classifier: Programming Language :: Python :: 3.11
Classifier: Programming Language :: Python :: 3 :: Only
Classifier: Topic :: Software Development :: Libraries :: Python Modules
Classifier: Topic :: Software Development :: Quality Assurance
Classifier: Topic :: Utilities
Requires-Python: >=3.7
Requires-Dist: flake8
Requires-Dist: parso
